markdownit/__init__.py
markdownit/admin.py
markdownit/apps.py
markdownit/migrations/__init__.py
markdownit/models.py
markdownit/templatetags/__init__.py
markdownit/templatetags/markdownit.py
markdownit/tests.py
markdownit/views.py
django_markdownit-0.5.0.dist-info/METADATA
django_markdownit-0.5.0.dist-info/WHEEL
django_markdownit-0.5.0.dist-info/RECORD
