Metadata-Version: 2.1
Name: django-markdownit
Version: 0.5.0
Summary: Markdown template filter for Django following CommonMark specs (markdown-it-py).
Home-page: https://github.com/noxan/django-markdownit
License: MIT
Keywords: django,markdown,commonmark
Author: Richard
Author-email: richard@stromer.org
Requires-Python: >=3.12,<4.0
Classifier: Environment :: Web Environment
Classifier: Framework :: Django
Classifier: License :: OSI Approved :: MIT License
Classifier: Programming Language :: Python :: 3
Classifier: Programming Language :: Python :: 3.12
Requires-Dist: django (>=4.0)
Requires-Dist: markdown-it-py (>=3.0.0,<4.0.0)
Requires-Dist: nh3 (>=0.2.14,<0.3.0)
Project-URL: Repository, https://github.com/noxan/django-markdownit
